{
    "pips": {},
    "sites": [],
    "tile_type": "RCLK_INTF_L_IBRK_PCIE4_R",
    "wires": {
        "CLK_HDISTR_FT0_0": null,
        "CLK_HDISTR_FT0_1": null,
        "CLK_HDISTR_FT0_2": null,
        "CLK_HDISTR_FT0_3": null,
        "CLK_HDISTR_FT0_4": null,
        "CLK_HDISTR_FT0_5": null,
        "CLK_HDISTR_FT0_6": null,
        "CLK_HDISTR_FT0_7": null,
        "CLK_HDISTR_FT0_8": null,
        "CLK_HDISTR_FT0_9": null,
        "CLK_HDISTR_FT0_10": null,
        "CLK_HDISTR_FT0_11": null,
        "CLK_HDISTR_FT0_12": null,
        "CLK_HDISTR_FT0_13": null,
        "CLK_HDISTR_FT0_14": null,
        "CLK_HDISTR_FT0_15": null,
        "CLK_HDISTR_FT0_16": null,
        "CLK_HDISTR_FT0_17": null,
        "CLK_HDISTR_FT0_18": null,
        "CLK_HDISTR_FT0_19": null,
        "CLK_HDISTR_FT0_20": null,
        "CLK_HDISTR_FT0_21": null,
        "CLK_HDISTR_FT0_22": null,
        "CLK_HDISTR_FT0_23": null,
        "CLK_HROUTE_FT0_0": null,
        "CLK_HROUTE_FT0_1": null,
        "CLK_HROUTE_FT0_2": null,
        "CLK_HROUTE_FT0_3": null,
        "CLK_HROUTE_FT0_4": null,
        "CLK_HROUTE_FT0_5": null,
        "CLK_HROUTE_FT0_6": null,
        "CLK_HROUTE_FT0_7": null,
        "CLK_HROUTE_FT0_8": null,
        "CLK_HROUTE_FT0_9": null,
        "CLK_HROUTE_FT0_10": null,
        "CLK_HROUTE_FT0_11": null,
        "CLK_HROUTE_FT0_12": null,
        "CLK_HROUTE_FT0_13": null,
        "CLK_HROUTE_FT0_14": null,
        "CLK_HROUTE_FT0_15": null,
        "CLK_HROUTE_FT0_16": null,
        "CLK_HROUTE_FT0_17": null,
        "CLK_HROUTE_FT0_18": null,
        "CLK_HROUTE_FT0_19": null,
        "CLK_HROUTE_FT0_20": null,
        "CLK_HROUTE_FT0_21": null,
        "CLK_HROUTE_FT0_22": null,
        "CLK_HROUTE_FT0_23": null,
        "INT_RCLK_TO_CLK_0_FT0_0": null,
        "INT_RCLK_TO_CLK_0_FT0_1": null,
        "INT_RCLK_TO_CLK_0_FT0_2": null,
        "INT_RCLK_TO_CLK_0_FT0_3": null,
        "INT_RCLK_TO_CLK_1_FT0_0": null,
        "INT_RCLK_TO_CLK_1_FT0_1": null,
        "INT_RCLK_TO_CLK_1_FT0_2": null,
        "INT_RCLK_TO_CLK_1_FT0_3": null
    }
}
