{
    "pips": {},
    "sites": [],
    "tile_type": "HPIO_RIGHT_TERM_B",
    "wires": {
        "AMS_IO_BUS_0_0": null,
        "AMS_IO_BUS_0_1": null,
        "AMS_IO_BUS_0_2": null,
        "AMS_IO_BUS_0_3": null,
        "AMS_IO_BUS_0_4": null,
        "AMS_IO_BUS_0_5": null,
        "AMS_IO_BUS_0_6": null,
        "AMS_IO_BUS_0_7": null,
        "AMS_IO_BUS_0_8": null,
        "AMS_IO_BUS_0_9": null,
        "AMS_IO_BUS_0_10": null,
        "AMS_IO_BUS_0_11": null,
        "AMS_IO_BUS_0_12": null,
        "AMS_IO_BUS_0_13": null,
        "AMS_IO_BUS_0_14": null,
        "AMS_IO_BUS_0_15": null,
        "AMS_IO_BUS_2_0": null,
        "AMS_IO_BUS_2_1": null,
        "AMS_IO_BUS_2_2": null,
        "AMS_IO_BUS_2_3": null,
        "AMS_IO_BUS_2_4": null,
        "AMS_IO_BUS_2_5": null,
        "AMS_IO_BUS_2_6": null,
        "AMS_IO_BUS_2_7": null,
        "AMS_IO_BUS_2_8": null,
        "AMS_IO_BUS_2_9": null,
        "AMS_IO_BUS_2_10": null,
        "AMS_IO_BUS_2_11": null,
        "AMS_IO_BUS_2_12": null,
        "AMS_IO_BUS_2_13": null,
        "AMS_IO_BUS_2_14": null,
        "AMS_IO_BUS_2_15": null,
        "CCIO_IO2RCLK0": null,
        "CCIO_IO2RCLK1": null,
        "CLOCK_DR_IN": null,
        "RESET_TAP_B_IN": null,
        "SHIFT_DR_IN": null
    }
}
